dyPolyChord/__init__.py
dyPolyChord/_version.py
dyPolyChord/nlive_allocation.py
dyPolyChord/output_processing.py
dyPolyChord/polychord_utils.py
dyPolyChord/pypolychord_utils.py
dyPolyChord/python_likelihoods.py
dyPolyChord/python_priors.py
dyPolyChord/run_dynamic_ns.py
dyPolyChord-0.1.1.dist-info/LICENSE
dyPolyChord-0.1.1.dist-info/METADATA
dyPolyChord-0.1.1.dist-info/WHEEL
dyPolyChord-0.1.1.dist-info/top_level.txt
dyPolyChord-0.1.1.dist-info/RECORD
