Metadata-Version: 2.1
Name: dyPolyChord
Version: 0.1.1
Summary: Super fast dynamic nested sampling with PolyChord (python, C++ and Fortran likelihoods).
Home-page: https://github.com/ejhigson/dyPolyChord
Author: Edward Higson
Author-email: e.higson@mrao.cam.ac.uk
License: MIT
Project-URL: Docs, http://dyPolyChord.readthedocs.io/en/latest/
Keywords: nested-sampling dynamic-nested-sampling
Platform: UNKNOWN
Classifier: Development Status :: 5 - Production/Stable
Classifier: Intended Audience :: Science/Research
Classifier: License :: OSI Approved :: MIT License
Classifier: Programming Language :: Python :: 2
Classifier: Programming Language :: Python :: 2.7
Classifier: Programming Language :: Python :: 3
Classifier: Programming Language :: Python :: 3.4
Classifier: Programming Language :: Python :: 3.5
Classifier: Programming Language :: Python :: 3.6
Classifier: Topic :: Scientific/Engineering :: Astronomy
Classifier: Topic :: Scientific/Engineering :: Physics
Classifier: Topic :: Scientific/Engineering :: Information Analysis
Requires-Dist: numpy (>=1.13)
Requires-Dist: scipy (>=1.0.0)
Requires-Dist: nestcheck (>=0.1.8)
Requires-Dist: futures ; python_version == "2.7"
Requires-Dist: pytz ; python_version == "2.7"
Requires-Dist: python-dateutil ; python_version == "2.7"
Provides-Extra: mpi
Requires-Dist: mpi4py ; extra == 'mpi'
Provides-Extra: docs
Requires-Dist: sphinx ; extra == 'docs'
Requires-Dist: numpydoc ; extra == 'docs'
Requires-Dist: sphinx-rtd-theme ; extra == 'docs'
Requires-Dist: nbsphinx (>=0.3.3) ; extra == 'docs'
